firestoretools/__init__.py
firestoretools/firestore_tools.py
firestoretools-0.1.2.dist-info/LICENSE.txt
firestoretools-0.1.2.dist-info/METADATA
firestoretools-0.1.2.dist-info/WHEEL
firestoretools-0.1.2.dist-info/entry_points.txt
firestoretools-0.1.2.dist-info/top_level.txt
firestoretools-0.1.2.dist-info/RECORD
