Metadata-Version: 2.1
Name: firestoretools
Version: 0.1.2
Summary: Useful tools to work with Google Firestore in Python
Home-page: https://github.com/ncthuc/firestoretools
Author: Thuc Nguyen
Author-email: gthuc.nguyen@gmail.com
License: MIT
Download-URL: https://pypi.org/project/firestoretools/
Keywords: Firestore,Firebase,Google Cloud,Python 3
Platform: UNKNOWN
Requires-Dist: click
Requires-Dist: firebase-admin
